[
    {
        "inputs": [],
        "stateMutability": "nonpayable",
        "type": "constructor"
    },
    {
        "inputs": [
            {
                "internalType": "address",
                "name": "owner",
                "type": "address"
            }
        ],
        "name": "OwnableInvalidOwner",
        "type": "error"
    },
    {
        "inputs": [
            {
                "internalType": "address",
                "name": "account",
                "type": "address"
            }
        ],
        "name": "OwnableUnauthorizedAccount",
        "type": "error"
    },
    {
        "anonymous": false,
        "inputs": [
            {
                "indexed": true,
                "internalType": "address",
                "name": "nftAddress",
                "type": "address"
            },
            {
                "indexed": false,
                "internalType": "string",
                "name": "name",
                "type": "string"
            },
            {
                "indexed": false,
                "internalType": "string",
                "name": "symbol",
                "type": "string"
            },
            {
                "indexed": false,
                "internalType": "address",
                "name": "owner",
                "type": "address"
            },
            {
                "indexed": false,
                "internalType": "uint256",
                "name": "mintLevel",
                "type": "uint256"
            },
            {
                "indexed": false,
                "internalType": "string",
                "name": "baseTokenURI",
                "type": "string"
            }
        ],
        "name": "NFTCreated",
        "type": "event"
    },
    {
        "anonymous": false,
        "inputs": [
            {
                "indexed": true,
                "internalType": "address",
                "name": "previousOwner",
                "type": "address"
            },
            {
                "indexed": true,
                "internalType": "address",
                "name": "newOwner",
                "type": "address"
            }
        ],
        "name": "OwnershipTransferred",
        "type": "event"
    },
    {
        "inputs": [
            {
                "internalType": "string",
                "name": "name",
                "type": "string"
            },
            {
                "internalType": "string",
                "name": "symbol",
                "type": "string"
            },
            {
                "internalType": "uint256",
                "name": "mintLevel",
                "type": "uint256"
            },
            {
                "internalType": "string",
                "name": "baseTokenURI",
                "type": "string"
            }
        ],
        "name": "createNFT",
        "outputs": [
            {
                "internalType": "address",
                "name": "",
                "type": "address"
            }
        ],
        "stateMutability": "nonpayable",
        "type": "function"
    },
    {
        "inputs": [
            {
                "internalType": "uint256",
                "name": "",
                "type": "uint256"
            }
        ],
        "name": "createdNFTs",
        "outputs": [
            {
                "internalType": "address",
                "name": "",
                "type": "address"
            }
        ],
        "stateMutability": "view",
        "type": "function"
    },
    {
        "inputs": [],
        "name": "getCreatedNFTs",
        "outputs": [
            {
                "internalType": "address[]",
                "name": "",
                "type": "address[]"
            }
        ],
        "stateMutability": "view",
        "type": "function"
    },
    {
        "inputs": [
            {
                "internalType": "uint256",
                "name": "start",
                "type": "uint256"
            },
            {
                "internalType": "uint256",
                "name": "end",
                "type": "uint256"
            }
        ],
        "name": "getCreatedNFTsByRange",
        "outputs": [
            {
                "internalType": "address[]",
                "name": "",
                "type": "address[]"
            }
        ],
        "stateMutability": "view",
        "type": "function"
    },
    {
        "inputs": [],
        "name": "getCreatedNFTsCount",
        "outputs": [
            {
                "internalType": "uint256",
                "name": "",
                "type": "uint256"
            }
        ],
        "stateMutability": "view",
        "type": "function"
    },
    {
        "inputs": [],
        "name": "owner",
        "outputs": [
            {
                "internalType": "address",
                "name": "",
                "type": "address"
            }
        ],
        "stateMutability": "view",
        "type": "function"
    },
    {
        "inputs": [],
        "name": "renounceOwnership",
        "outputs": [],
        "stateMutability": "nonpayable",
        "type": "function"
    },
    {
        "inputs": [
            {
                "internalType": "address",
                "name": "newOwner",
                "type": "address"
            }
        ],
        "name": "transferOwnership",
        "outputs": [],
        "stateMutability": "nonpayable",
        "type": "function"
    }
]